<?xml version="1.0" encoding="utf-8"?>
<ArrayOfSendListProductToSubDealers xmlns:xsi="http://www.w3.org/2001/XMLSchema-instance" xmlns:xsd="http://www.w3.org/2001/XMLSchema">
  <SendListProductToSubDealers>
    <sendID>1</sendID>
    <brandIDFK>0</brandIDFK>
    <brandName>SHİMANO</brandName>
    <categoryIDFK>0</categoryIDFK>
    <categoryName>FRONT DERAİLLEUR</categoryName>
    <productIDFK>0</productIDFK>
    <productItemNumber>md3</productItemNumber>
    <productName>TOURNEY G540</productName>
    <productDescription>düzenlendi 23:38</productDescription>
    <mainUserIDFK>0</mainUserIDFK>
    <subDealerUserIDFK>0</subDealerUserIDFK>
    <subDealerName>Gold Bike</subDealerName>
    <sendDate>2025-05-01T20:40:00.21</sendDate>
    <sendQuantity>2</sendQuantity>
    <unitPrice>495.00</unitPrice>
    <subTotalPrice>990.00</subTotalPrice>
    <tax>15.00</tax>
    <totalPrice>1138.50</totalPrice>
    <discountedPrice>1024.65</discountedPrice>
    <productImageName>5801f1e6-68c8-4144-b587-f796b9a3c2ab.jpg</productImageName>
  </SendListProductToSubDealers>
  <SendListProductToSubDealers>
    <sendID>3</sendID>
    <brandIDFK>0</brandIDFK>
    <brandName>TREK</brandName>
    <categoryIDFK>0</categoryIDFK>
    <categoryName>BODY</categoryName>
    <productIDFK>0</productIDFK>
    <productItemNumber>md1</productItemNumber>
    <productName>EMONDA SL 500</productName>
    <productDescription />
    <mainUserIDFK>0</mainUserIDFK>
    <subDealerUserIDFK>0</subDealerUserIDFK>
    <subDealerName>Silver Bike</subDealerName>
    <sendDate>2025-05-01T23:51:31.927</sendDate>
    <sendQuantity>3</sendQuantity>
    <unitPrice>10250.00</unitPrice>
    <subTotalPrice>30750.00</subTotalPrice>
    <tax>15.00</tax>
    <totalPrice>35362.50</totalPrice>
    <discountedPrice>33594.38</discountedPrice>
    <productImageName>2596442e-49d8-4180-8eb9-d77e7a430ed8.jpg</productImageName>
  </SendListProductToSubDealers>
  <SendListProductToSubDealers>
    <sendID>4</sendID>
    <brandIDFK>0</brandIDFK>
    <brandName>SHİMANO</brandName>
    <categoryIDFK>0</categoryIDFK>
    <categoryName>FRONT DERAİLLEUR</categoryName>
    <productIDFK>0</productIDFK>
    <productItemNumber>md3</productItemNumber>
    <productName>TOURNEY G540</productName>
    <productDescription />
    <mainUserIDFK>0</mainUserIDFK>
    <subDealerUserIDFK>0</subDealerUserIDFK>
    <subDealerName>Bronze Bike</subDealerName>
    <sendDate>2025-05-02T00:25:21.843</sendDate>
    <sendQuantity>2</sendQuantity>
    <unitPrice>495.00</unitPrice>
    <subTotalPrice>990.00</subTotalPrice>
    <tax>15.00</tax>
    <totalPrice>1138.50</totalPrice>
    <discountedPrice>1115.73</discountedPrice>
    <productImageName>5801f1e6-68c8-4144-b587-f796b9a3c2ab.jpg</productImageName>
  </SendListProductToSubDealers>
  <SendListProductToSubDealers>
    <sendID>1</sendID>
    <brandIDFK>0</brandIDFK>
    <brandName>SHİMANO</brandName>
    <categoryIDFK>0</categoryIDFK>
    <categoryName>FRONT DERAİLLEUR</categoryName>
    <productIDFK>0</productIDFK>
    <productItemNumber>md3</productItemNumber>
    <productName>TOURNEY G540</productName>
    <productDescription>düzenlendi 23:38</productDescription>
    <mainUserIDFK>0</mainUserIDFK>
    <subDealerUserIDFK>0</subDealerUserIDFK>
    <subDealerName>Gold Bike</subDealerName>
    <sendDate>2025-05-01T20:40:00.21</sendDate>
    <sendQuantity>2</sendQuantity>
    <unitPrice>495.00</unitPrice>
    <subTotalPrice>990.00</subTotalPrice>
    <tax>15.00</tax>
    <totalPrice>1138.50</totalPrice>
    <discountedPrice>1024.65</discountedPrice>
    <productImageName>5801f1e6-68c8-4144-b587-f796b9a3c2ab.jpg</productImageName>
  </SendListProductToSubDealers>
  <SendListProductToSubDealers>
    <sendID>3</sendID>
    <brandIDFK>0</brandIDFK>
    <brandName>TREK</brandName>
    <categoryIDFK>0</categoryIDFK>
    <categoryName>BODY</categoryName>
    <productIDFK>0</productIDFK>
    <productItemNumber>md1</productItemNumber>
    <productName>EMONDA SL 500</productName>
    <productDescription />
    <mainUserIDFK>0</mainUserIDFK>
    <subDealerUserIDFK>0</subDealerUserIDFK>
    <subDealerName>Silver Bike</subDealerName>
    <sendDate>2025-05-01T23:51:31.927</sendDate>
    <sendQuantity>3</sendQuantity>
    <unitPrice>10250.00</unitPrice>
    <subTotalPrice>30750.00</subTotalPrice>
    <tax>15.00</tax>
    <totalPrice>35362.50</totalPrice>
    <discountedPrice>33594.38</discountedPrice>
    <productImageName>2596442e-49d8-4180-8eb9-d77e7a430ed8.jpg</productImageName>
  </SendListProductToSubDealers>
  <SendListProductToSubDealers>
    <sendID>4</sendID>
    <brandIDFK>0</brandIDFK>
    <brandName>SHİMANO</brandName>
    <categoryIDFK>0</categoryIDFK>
    <categoryName>FRONT DERAİLLEUR</categoryName>
    <productIDFK>0</productIDFK>
    <productItemNumber>md3</productItemNumber>
    <productName>TOURNEY G540</productName>
    <productDescription />
    <mainUserIDFK>0</mainUserIDFK>
    <subDealerUserIDFK>0</subDealerUserIDFK>
    <subDealerName>Bronze Bike</subDealerName>
    <sendDate>2025-05-02T00:25:21.843</sendDate>
    <sendQuantity>2</sendQuantity>
    <unitPrice>495.00</unitPrice>
    <subTotalPrice>990.00</subTotalPrice>
    <tax>15.00</tax>
    <totalPrice>1138.50</totalPrice>
    <discountedPrice>1115.73</discountedPrice>
    <productImageName>5801f1e6-68c8-4144-b587-f796b9a3c2ab.jpg</productImageName>
  </SendListProductToSubDealers>
  <SendListProductToSubDealers>
    <sendID>1</sendID>
    <brandIDFK>0</brandIDFK>
    <brandName>SHİMANO</brandName>
    <categoryIDFK>0</categoryIDFK>
    <categoryName>FRONT DERAİLLEUR</categoryName>
    <productIDFK>0</productIDFK>
    <productItemNumber>md3</productItemNumber>
    <productName>TOURNEY G540</productName>
    <productDescription>düzenlendi 23:38</productDescription>
    <mainUserIDFK>0</mainUserIDFK>
    <subDealerUserIDFK>0</subDealerUserIDFK>
    <subDealerName>Gold Bike</subDealerName>
    <sendDate>2025-05-01T20:40:00.21</sendDate>
    <sendQuantity>2</sendQuantity>
    <unitPrice>495.00</unitPrice>
    <subTotalPrice>990.00</subTotalPrice>
    <tax>15.00</tax>
    <totalPrice>1138.50</totalPrice>
    <discountedPrice>1024.65</discountedPrice>
    <productImageName>5801f1e6-68c8-4144-b587-f796b9a3c2ab.jpg</productImageName>
  </SendListProductToSubDealers>
  <SendListProductToSubDealers>
    <sendID>3</sendID>
    <brandIDFK>0</brandIDFK>
    <brandName>TREK</brandName>
    <categoryIDFK>0</categoryIDFK>
    <categoryName>BODY</categoryName>
    <productIDFK>0</productIDFK>
    <productItemNumber>md1</productItemNumber>
    <productName>EMONDA SL 500</productName>
    <productDescription />
    <mainUserIDFK>0</mainUserIDFK>
    <subDealerUserIDFK>0</subDealerUserIDFK>
    <subDealerName>Silver Bike</subDealerName>
    <sendDate>2025-05-01T23:51:31.927</sendDate>
    <sendQuantity>3</sendQuantity>
    <unitPrice>10250.00</unitPrice>
    <subTotalPrice>30750.00</subTotalPrice>
    <tax>15.00</tax>
    <totalPrice>35362.50</totalPrice>
    <discountedPrice>33594.38</discountedPrice>
    <productImageName>2596442e-49d8-4180-8eb9-d77e7a430ed8.jpg</productImageName>
  </SendListProductToSubDealers>
  <SendListProductToSubDealers>
    <sendID>4</sendID>
    <brandIDFK>0</brandIDFK>
    <brandName>SHİMANO</brandName>
    <categoryIDFK>0</categoryIDFK>
    <categoryName>FRONT DERAİLLEUR</categoryName>
    <productIDFK>0</productIDFK>
    <productItemNumber>md3</productItemNumber>
    <productName>TOURNEY G540</productName>
    <productDescription />
    <mainUserIDFK>0</mainUserIDFK>
    <subDealerUserIDFK>0</subDealerUserIDFK>
    <subDealerName>Bronze Bike</subDealerName>
    <sendDate>2025-05-02T00:25:21.843</sendDate>
    <sendQuantity>2</sendQuantity>
    <unitPrice>495.00</unitPrice>
    <subTotalPrice>990.00</subTotalPrice>
    <tax>15.00</tax>
    <totalPrice>1138.50</totalPrice>
    <discountedPrice>1115.73</discountedPrice>
    <productImageName>5801f1e6-68c8-4144-b587-f796b9a3c2ab.jpg</productImageName>
  </SendListProductToSubDealers>
</ArrayOfSendListProductToSubDealers>